astrophot/AP_config.py
astrophot/__init__.py
astrophot/__main__.py
astrophot/_version.py
astrophot/errors/__init__.py
astrophot/errors/base.py
astrophot/errors/fit.py
astrophot/errors/image.py
astrophot/errors/models.py
astrophot/errors/param.py
astrophot/fit/__init__.py
astrophot/fit/base.py
astrophot/fit/gp.py
astrophot/fit/gradient.py
astrophot/fit/hmc.py
astrophot/fit/iterative.py
astrophot/fit/lm.py
astrophot/fit/mhmcmc.py
astrophot/fit/minifit.py
astrophot/fit/nuts.py
astrophot/fit/oldlm.py
astrophot/image/__init__.py
astrophot/image/image_header.py
astrophot/image/image_object.py
astrophot/image/jacobian_image.py
astrophot/image/model_image.py
astrophot/image/psf_image.py
astrophot/image/target_image.py
astrophot/image/wcs.py
astrophot/image/window_object.py
astrophot/models/__init__.py
astrophot/models/_model_methods.py
astrophot/models/_shared_methods.py
astrophot/models/airy_psf.py
astrophot/models/core_model.py
astrophot/models/edgeon_model.py
astrophot/models/eigen_psf.py
astrophot/models/exponential_model.py
astrophot/models/flatsky_model.py
astrophot/models/foureirellipse_model.py
astrophot/models/galaxy_model_object.py
astrophot/models/gaussian_model.py
astrophot/models/group_model_object.py
astrophot/models/group_psf_model.py
astrophot/models/model_object.py
astrophot/models/moffat_model.py
astrophot/models/multi_gaussian_expansion_model.py
astrophot/models/nuker_model.py
astrophot/models/pixelated_psf_model.py
astrophot/models/planesky_model.py
astrophot/models/point_source.py
astrophot/models/psf_model_object.py
astrophot/models/ray_model.py
astrophot/models/relspline_model.py
astrophot/models/sersic_model.py
astrophot/models/sky_model_object.py
astrophot/models/spline_model.py
astrophot/models/superellipse_model.py
astrophot/models/warp_model.py
astrophot/models/wedge_model.py
astrophot/models/zernike_model.py
astrophot/param/__init__.py
astrophot/param/base.py
astrophot/param/param_context.py
astrophot/param/parameter.py
astrophot-0.16.13.dist-info/METADATA
astrophot-0.16.13.dist-info/WHEEL
astrophot-0.16.13.dist-info/entry_points.txt
astrophot-0.16.13.dist-info/licenses/LICENSE
astrophot-0.16.13.dist-info/RECORD
