Metadata-Version: 2.4
Name: astrophot
Version: 0.16.13
Summary: A fast, flexible, automated, and differentiable astronomical image 2D forward modelling tool for precise parallel multi-wavelength photometry.
Project-URL: Homepage, https://autostronomy.github.io/AstroPhot/
Project-URL: Documentation, https://autostronomy.github.io/AstroPhot/
Project-URL: Repository, https://github.com/Autostronomy/AstroPhot
Project-URL: Issues, https://github.com/Autostronomy/AstroPhot/issues
Author-email: Connor Stone <connorstone628@gmail.com>
License:                     GNU GENERAL PUBLIC LICENSE
License-File: LICENSE
Keywords: astronomy,astrophot,astrophysics,differentiable programming,photometry,pytorch,scientific computing
Classifier: Development Status :: 1 - Planning
Classifier: Intended Audience :: Science/Research
Classifier: License :: OSI Approved :: GNU General Public License v3 (GPLv3)
Classifier: Operating System :: OS Independent
Classifier: Programming Language :: Python :: 3
Requires-Python: >=3.9
Requires-Dist: astropy>=5.3
Requires-Dist: h5py>=3.8.0
Requires-Dist: matplotlib>=3.7
Requires-Dist: numpy<2.0.0,>=1.24.0
Requires-Dist: pyro-ppl>=1.8.0
Requires-Dist: pyyaml>=6.0
Requires-Dist: requests>=2.30.0
Requires-Dist: scipy>=1.10.0
Requires-Dist: torch>=2.0.0
Requires-Dist: tqdm>=4.65.0
